rest_api_lib_creator/__init__.py
rest_api_lib_creator/core.py
rest_api_lib_creator/datastructures.py
rest_api_lib_creator/mixins.py
rest_api_lib_creator/pagination_classes.py
rest_api_lib_creator/utils.py
rest_api_lib_creator-0.4.0.dist-info/LICENSE
rest_api_lib_creator-0.4.0.dist-info/METADATA
rest_api_lib_creator-0.4.0.dist-info/WHEEL
rest_api_lib_creator-0.4.0.dist-info/top_level.txt
rest_api_lib_creator-0.4.0.dist-info/RECORD
