Metadata-Version: 2.1
Name: rest-api-lib-creator
Version: 0.4.0
Summary: Boilerplate-free way for creating libs for REST APIs
Home-page: UNKNOWN
Author: Filipe Waitman
Author-email: filwaitman@gmail.com
License: MIT
Project-URL: Source, https://github.com/filwaitman/rest-api-lib-creator
Platform: UNKNOWN
Classifier: Development Status :: 3 - Alpha
Classifier: Intended Audience :: Developers
Classifier: License :: OSI Approved :: MIT License
Classifier: Operating System :: OS Independent
Classifier: Programming Language :: Python
Classifier: Programming Language :: Python :: 3
Classifier: Programming Language :: Python :: 3.6
Classifier: Programming Language :: Python :: 3.7
Classifier: Programming Language :: Python :: 3.8
Requires-Dist: requests
